docsray/__init__.py
docsray/cli.py
docsray/config.py
docsray/server.py
docsray/cli/cache_manager.py
docsray/providers/__init__.py
docsray/providers/base.py
docsray/providers/llamaparse.py
docsray/providers/pymupdf4llm.py
docsray/providers/registry.py
docsray/tools/__init__.py
docsray/tools/extract.py
docsray/tools/map.py
docsray/tools/peek.py
docsray/tools/seek.py
docsray/tools/xray.py
docsray/utils/__init__.py
docsray/utils/cache.py
docsray/utils/documents.py
docsray/utils/llamaparse_cache.py
docsray/utils/logging.py
docsray_mcp-0.3.3.dist-info/licenses/LICENSE
docsray_mcp-0.3.3.dist-info/METADATA
docsray_mcp-0.3.3.dist-info/WHEEL
docsray_mcp-0.3.3.dist-info/entry_points.txt
docsray_mcp-0.3.3.dist-info/top_level.txt
docsray_mcp-0.3.3.dist-info/RECORD
