Metadata-Version: 2.4
Name: docsray-mcp
Version: 0.3.3
Summary: AI-powered document perception and analysis MCP server with intelligent provider selection
Author-email: Docsray Team <team@docsray.dev>
License-Expression: Apache-2.0
Project-URL: Homepage, https://docsray.dev
Project-URL: Documentation, https://docsray.dev
Project-URL: Repository, https://github.com/xingh/docsray-mcp
Project-URL: Issues, https://github.com/xingh/docsray-mcp/issues
Keywords: mcp,document,pdf,ai,llm,analysis,extraction,llamaparse,mistral-ocr,ocrmypdf,tesseract
Classifier: Development Status :: 4 - Beta
Classifier: Intended Audience :: Developers
Classifier: Programming Language :: Python :: 3
Classifier: Programming Language :: Python :: 3.9
Classifier: Programming Language :: Python :: 3.10
Classifier: Programming Language :: Python :: 3.11
Classifier: Programming Language :: Python :: 3.12
Classifier: Topic :: Software Development :: Libraries
Classifier: Topic :: Text Processing :: General
Requires-Python: >=3.9
License-File: LICENSE
Requires-Dist: fastmcp>=2.11.1
Requires-Dist: pymupdf4llm>=0.0.17
Requires-Dist: httpx>=0.27.0
Requires-Dist: pydantic>=2.0.0
Requires-Dist: python-dotenv>=1.0.0
Requires-Dist: typing-extensions>=4.0.0
Requires-Dist: aiofiles>=24.0.0
Requires-Dist: click>=8.0.0
Requires-Dist: nest-asyncio>=1.5.0
Provides-Extra: ocr
Requires-Dist: pytesseract>=0.3.10; extra == "ocr"
Requires-Dist: ocrmypdf>=16.0.0; extra == "ocr"
Requires-Dist: pillow>=10.0.0; extra == "ocr"
Provides-Extra: ai
Requires-Dist: mistralai>=1.0.0; extra == "ai"
Requires-Dist: llama-parse>=0.6.0; extra == "ai"
Provides-Extra: dev
Requires-Dist: pytest>=8.0.0; extra == "dev"
Requires-Dist: pytest-asyncio>=0.24.0; extra == "dev"
Requires-Dist: pytest-cov>=5.0.0; extra == "dev"
Requires-Dist: pytest-mock>=3.14.0; extra == "dev"
Requires-Dist: black>=24.0.0; extra == "dev"
Requires-Dist: ruff>=0.5.0; extra == "dev"
Requires-Dist: mypy>=1.0.0; extra == "dev"
Requires-Dist: types-aiofiles; extra == "dev"
Provides-Extra: all
Requires-Dist: docsray-mcp[ai,dev,ocr]; extra == "all"
Dynamic: license-file
